CHANGES.txt
LICENSE.txt
MANIFEST.in
README.txt
setup.py
todo.txt
painted_word.egg-info/PKG-INFO
painted_word.egg-info/SOURCES.txt
painted_word.egg-info/dependency_links.txt
painted_word.egg-info/requires.txt
painted_word.egg-info/top_level.txt
paintedword/__init__.py
paintedword/admin.py
paintedword/forms.py
paintedword/models.py
paintedword/settings.py
paintedword/urls.py
paintedword/views.py
paintedword/wsgi.py
paintedword/static/css/jquery.Jcrop.css
paintedword/static/css/jquery.SimpleCropper.css
paintedword/static/css/jquery.cropbox.css
paintedword/static/css/paintedword.css
paintedword/static/img/Cancel.png
paintedword/static/img/CancelRed.png
paintedword/static/img/Jcrop.gif
paintedword/static/img/Ok.png
paintedword/static/img/OkGreen.png
paintedword/static/img/ajax-loader.gif
paintedword/static/img/grey.gif
paintedword/static/js/paintedword.js
paintedword/static/js/paintedword_ie.js
paintedword/static/js/libs/jquery-1.7.2.min.js
paintedword/static/js/libs/modernizr-2.5.3.min.js
paintedword/static/js/plugins/facebook-canvas.js
paintedword/static/js/plugins/flash10canvas.swf
paintedword/static/js/plugins/flash9canvas.swf
paintedword/static/js/plugins/flashcanvas.js
paintedword/static/js/plugins/hammer.min.js
paintedword/static/js/plugins/jquery.Jcrop.min.js
paintedword/static/js/plugins/jquery.cropbox.js
paintedword/static/js/plugins/jquery.form.js
paintedword/static/js/plugins/load-image.all.min.js
paintedword/templates/gallery.html
paintedword/templates/paintedword_scripts.html
paintedword/templates/paintedword_styles.html
paintedword/templates/photo_upload.html
paintedword/templatetags/__init__.py
paintedword/templatetags/paintedword_tags.py