Metadata-Version: 1.0
Name: painted-word
Version: 0.1.4
Summary: A set of helpers for building an image based campaign.  Plays nicely with the Actionkit CRM.
Home-page: https://github.com/mvattuone/painted-word
Author: Mike Vattuone
Author-email: mvattuone@gmail.com
License: LICENSE.txt
Platform: UNKNOWN
